{
	"description": null,
	"ImageLocation": null,
	"XP": 0,
	"Coin": {
		"Copper": 0,
		"Silver": 0,
		"Gold": 0,
		"Electrum": 0,
		"Platinum": 0,
		"Total": 0
	},
	"level": "1",
	"name": "Name",
	"class": "Wizard",
	"strength": 12,
	"dexterity": 18,
	"constitution": 18,
	"intelligence": 18,
	"wisdom": 14,
	"charisma": 14,
	"armor_class": 16,
	"speed": "30",
	"hitPoints": 10,
	"temp_hit_points": 0,
	"riders": [],
	"Cantrips": [],
	"Level4": []
	"Level5": [],
	"Level6": [],
	"Level7": [],
	"Level8": [],
	"Level9": [],
	"damage_resistances": null,
	"damage_vulnerabilities": null,
	"damage_immunities": null,
	"senses": null,
	"Languages": "common"
}