{
  "Name": "CONE OF COLD",
  "Level": "5th-levei",
  "School": "evocation",
  "CastingTime": "I action",
  "Range": "5elf (60-foot cone)",
  "Components": "V,5, M(asmall crystal or glass cone)",
  "Duration": "Instantaneous",
  "Description": "Ablast ofcold air erupts from your hands. Eachcreature in a60-foot cone must make aConstitutionsaving throw. Acreature takes 8d8 cold damage onafailed save, or half as much damage on asuccessful one.Acreature killed bythis spell becomes afrozen statueuntil itthaws.At Higher LeveIs. When you cast this speIl using aspell slot of6th levelor higher, the damage increases byld8 foreach slot leveIabove 5th."
}