{
  "Name": "DISINTEGRATE",
  "Level": "6th-levei",
  "School": "transmutation",
  "CastingTime": "1action",
  "Range": "60 feet",
  "Components": "V,S, M(a lodestone and a pinch ofdust)",
  "Duration": "lnstantaneous",
  "Description": "Athin green ray springs from your pointing finger to atarget that you can see within range. The target can be acreature, an objecl, or a creation ofmagical force, suchas the wall created by wall offorce.Acreature targeted by this spell must make aDexterity saving throw. On a failed save, the target takesIOd6 +40 force damage. Iflhis damage reduces thetarget to Ohit points, it is disintegrated.Adisintegrated creature and everything ilis wearingand carrying, except magic ilems, are reduced to a pileof fine gray dust. The creature can be restored to lifeonly bymeans ofa true resurrection or a wish spell.This spell automatically disintegrates a Large orsmaller nonmagical object or a creation ofmagicalforce. ]fthe target is a Huge or larger object or creationofforce, this spell disintegrates a lO-foot-cube portion ofit.Amagic item is unaffecled by this spell.At Higher LeveIs. When you cast this spell using aspell slot of 7th leveIor higher, the damage increases by3d6 for each slot levei above 6th."
}