{
  "Name": "LOCATE OBJECT",
  "Level": "2nd-leveI",
  "School": "divinatian",
  "CastingTime": "1action",
  "Range": "Self",
  "Components": "V,S, M(afarked twig)",
  "Duration": "Cancentration, up to 10minutes",
  "Description": "Describe ar name an object that isfamiliar toyou.Vousense the direction tothe object's location, as lang asthat object iswithin 1,000 feetafyou.Ifthe object isinmotion, yau know the direction ofitsmovement.The spell can locate aspecific object known toyou,as longasyou haveseen itupclose-within 30 feet-atleast once, Alternatively, the spel1can locate the nearestabject ofaparticular kind, such as a certain kind ofapparel, jewelry, furniture, tool,ar weapon.This spel1can't locate an object ifanythickness oflead, evenathin sheet, blocks adirect path between youand the object."
}