{"description":null,"ImageLocation":null,"challenge_rating":"1","special_abilities":[{"name":"Keen Sight","desc":"The eagle has advantage on Wisdom (Perception) checks that rely on sight."}],"actions":[{"name":"Multiattack","desc":"The eagle makes two attacks: one with its beak and one with its talons."},{"name":"Beak","desc":"Melee Weapon Attack: +5 to hit, reach 5 ft., one target. Hit: 6 (1d6 + 3) piercing damage."},{"name":"Talons","desc":"Melee Weapon Attack: +5 to hit, reach 5 ft., one target. Hit: 10 (2d6 + 3) slashing damage."}],"hit_dice":"4d10","level":"1","name":"Giant Eagle","class":"beast","strength":16,"dexterity":17,"constitution":13,"intelligence":8,"wisdom":14,"charisma":10,"armor_class":13,"speed":"10 ft., fly 80 ft.","hitPoints":27,"temp_hit_points":0,"damage_log":[],"riders":[],"Cantrips":[],"Level1":[],"Level2":[],"Level3":[],"Level4":[],"Level5":[],"Level6":[],"Level7":[],"Level8":[],"Level9":[],"damage_resistances":"","damage_vulnerabilities":"","damage_immunities":"","senses":"passive Perception 14","Languages":"Giant Eagle, understands Common and Auran but can't speak"}